prosopopee/__init__.py
prosopopee/autogen.py
prosopopee/cache.py
prosopopee/prosopopee.py
prosopopee/utils.py
prosopopee/themes/exposure/static/css/baguetteBox.min.css
prosopopee/themes/exposure/static/css/encrypt.css
prosopopee/themes/exposure/static/css/fonts.css
prosopopee/themes/exposure/static/css/mediaelementplayer.css
prosopopee/themes/exposure/static/css/mejs-controls.svg
prosopopee/themes/exposure/static/css/panorama_viewer.css
prosopopee/themes/exposure/static/css/style-page.css
prosopopee/themes/exposure/static/css/style.css
prosopopee/themes/exposure/static/fonts/crimsontext-bold-webfont.eot
prosopopee/themes/exposure/static/fonts/crimsontext-bold-webfont.svg
prosopopee/themes/exposure/static/fonts/crimsontext-bold-webfont.ttf
prosopopee/themes/exposure/static/fonts/crimsontext-bold-webfont.woff
prosopopee/themes/exposure/static/fonts/crimsontext-bold-webfont.woff2
prosopopee/themes/exposure/static/fonts/crimsontext-bolditalic-webfont.eot
prosopopee/themes/exposure/static/fonts/crimsontext-bolditalic-webfont.svg
prosopopee/themes/exposure/static/fonts/crimsontext-bolditalic-webfont.ttf
prosopopee/themes/exposure/static/fonts/crimsontext-bolditalic-webfont.woff
prosopopee/themes/exposure/static/fonts/crimsontext-bolditalic-webfont.woff2
prosopopee/themes/exposure/static/fonts/crimsontext-italic-webfont.eot
prosopopee/themes/exposure/static/fonts/crimsontext-italic-webfont.svg
prosopopee/themes/exposure/static/fonts/crimsontext-italic-webfont.ttf
prosopopee/themes/exposure/static/fonts/crimsontext-italic-webfont.woff
prosopopee/themes/exposure/static/fonts/crimsontext-italic-webfont.woff2
prosopopee/themes/exposure/static/fonts/crimsontext-regular-webfont.eot
prosopopee/themes/exposure/static/fonts/crimsontext-regular-webfont.svg
prosopopee/themes/exposure/static/fonts/crimsontext-regular-webfont.ttf
prosopopee/themes/exposure/static/fonts/crimsontext-regular-webfont.woff
prosopopee/themes/exposure/static/fonts/crimsontext-regular-webfont.woff2
prosopopee-1.1.5.dist-info/LICENSE
prosopopee-1.1.5.dist-info/METADATA
prosopopee-1.1.5.dist-info/WHEEL
prosopopee-1.1.5.dist-info/entry_points.txt
prosopopee-1.1.5.dist-info/top_level.txt
prosopopee-1.1.5.dist-info/RECORD
