Metadata-Version: 2.1
Name: prosopopee
Version: 1.1.5
Summary: A static website generator that allows you to tell a story with your pictures
Home-page: https://github.com/Psycojoker/prosopopee
Author: Laurent Peuch
Author-email: cortex@worlddomination.be
License: GPLv3+
Platform: UNKNOWN
Requires-Dist: Babel
Requires-Dist: jinja2
Requires-Dist: path.py
Requires-Dist: ruamel.yaml
Requires-Dist: future
Requires-Dist: pillow (>=6)
